odoo/addons/l10n_ch_bank/README.rst
odoo/addons/l10n_ch_bank/__init__.py
odoo/addons/l10n_ch_bank/__manifest__.py
odoo/addons/l10n_ch_bank/data/res.bank.csv
odoo/addons/l10n_ch_bank/i18n/de.po
odoo/addons/l10n_ch_bank/i18n/fr.po
odoo/addons/l10n_ch_bank/i18n/it.po
odoo/addons/l10n_ch_bank/i18n/nb_NO.po
odoo/addons/l10n_ch_bank/models/__init__.py
odoo/addons/l10n_ch_bank/models/bank.py
odoo/addons/l10n_ch_bank/static/description/icon.png
odoo11_addon_l10n_ch_bank-11.0.1.0.2.dist-info/DESCRIPTION.rst
odoo11_addon_l10n_ch_bank-11.0.1.0.2.dist-info/METADATA
odoo11_addon_l10n_ch_bank-11.0.1.0.2.dist-info/RECORD
odoo11_addon_l10n_ch_bank-11.0.1.0.2.dist-info/WHEEL
odoo11_addon_l10n_ch_bank-11.0.1.0.2.dist-info/metadata.json
odoo11_addon_l10n_ch_bank-11.0.1.0.2.dist-info/top_level.txt
